index.py
auth/__init__.py
auth/eks_oidc_client.py
auth/oidc_client.py
auth/rbac_manager.py
chaos/__init__.py
chaos/aws_chaos.py
chaos/dns_chaos.py
chaos/experiment_manager.py
chaos/io_chaos.py
chaos/network_chaos.py
chaos/pod_chaos.py
chaos/remote_cluster_manager.py
chaos/stress_chaos.py
chaos/templates.py
chaos/time_chaos.py
chaos/validator.py
k8s/__init__.py
k8s/client.py
k8s/cluster_manager.py
k8s/resource_manager.py
utils/__init__.py
utils/config.py
utils/logger.py
utils/progress.py
chaos_mesh_mcp_server-6.2.0.dist-info/METADATA
chaos_mesh_mcp_server-6.2.0.dist-info/WHEEL
chaos_mesh_mcp_server-6.2.0.dist-info/entry_points.txt
chaos_mesh_mcp_server-6.2.0.dist-info/top_level.txt
chaos_mesh_mcp_server-6.2.0.dist-info/RECORD
