Metadata-Version: 2.4
Name: chaos-mesh-mcp-server
Version: 6.2.0
Summary: MCP Server for Chaos Engineering with Chaos Mesh on EKS
Author-email: Kandy Oh <kandy@plaintexting.com>
License: MIT
Classifier: Development Status :: 4 - Beta
Classifier: Intended Audience :: Developers
Classifier: License :: OSI Approved :: MIT License
Classifier: Programming Language :: Python :: 3
Classifier: Programming Language :: Python :: 3.12
Requires-Python: >=3.12
Requires-Dist: mcp>=1.3.0
Requires-Dist: kubernetes>=32.1.0
Requires-Dist: PyJWT>=2.8.0
Requires-Dist: cryptography>=41.0.0
Requires-Dist: requests>=2.31.0
Requires-Dist: pydantic>=2.5.0
Requires-Dist: pyyaml>=6.0.1
Requires-Dist: aiohttp>=3.9.0
Requires-Dist: asyncio-mqtt>=0.16.0
Requires-Dist: python-dotenv>=1.0.0
Requires-Dist: structlog>=23.2.0
Requires-Dist: tenacity>=8.2.3
Requires-Dist: boto3>=1.40.0
